fastapi_poe/__init__.py
fastapi_poe/base.py
fastapi_poe/client.py
fastapi_poe/py.typed
fastapi_poe/sync_utils.py
fastapi_poe/templates.py
fastapi_poe/types.py
fastapi_poe-0.0.83.dist-info/METADATA
fastapi_poe-0.0.83.dist-info/WHEEL
fastapi_poe-0.0.83.dist-info/licenses/LICENSE
fastapi_poe-0.0.83.dist-info/RECORD
