Metadata-Version: 2.4
Name: fastapi_poe
Version: 0.0.83
Summary: A demonstration of the Poe protocol using FastAPI
Project-URL: Homepage, https://creator.poe.com/
Author-email: Yusheng Ding <yding@quora.com>, Kris Yang <kryang@quora.com>, John Li <jli@quora.com>
License-File: LICENSE
Classifier: License :: OSI Approved :: Apache Software License
Classifier: Operating System :: OS Independent
Classifier: Programming Language :: Python :: 3
Requires-Python: >=3.9
Requires-Dist: fastapi
Requires-Dist: httpx
Requires-Dist: httpx-sse
Requires-Dist: pydantic>2
Requires-Dist: sse-starlette>=2.2.1
Requires-Dist: typing-extensions>=4.5.0
Requires-Dist: uvicorn
Provides-Extra: dev
Requires-Dist: pytest; extra == 'dev'
Requires-Dist: pytest-asyncio; extra == 'dev'
Requires-Dist: pytest-cov; extra == 'dev'
